xbrlld/__init__.py
xbrlld/cli.py
xbrlld/instance.py
xbrlld/taxonomy.py
xbrlld-0.2.2.dist-info/METADATA
xbrlld-0.2.2.dist-info/WHEEL
xbrlld-0.2.2.dist-info/entry_points.txt
xbrlld-0.2.2.dist-info/licenses/LICENCE
xbrlld-0.2.2.dist-info/RECORD
