Metadata-Version: 2.4
Name: xbrlld
Version: 0.2.2
Summary: A command line tool to convert XBRL taxonomies and instance documents into RDF.
Project-URL: Homepage, https://github.com/rossbowen/xbrlld
Author: rossbowen
License-File: LICENCE
Requires-Python: >=3.12
Requires-Dist: arelle-release>=2.36.29
Requires-Dist: click>=8.1.8
Requires-Dist: pytest>=8.4.1
Requires-Dist: rdflib>=7.1.3
